zonar_ds_env_arg_parser/__init__.py
zonar_ds_env_arg_parser/env_arg_parser.py
zonar_ds_env_arg_parser-1.0.1.dist-info/LICENSE
zonar_ds_env_arg_parser-1.0.1.dist-info/METADATA
zonar_ds_env_arg_parser-1.0.1.dist-info/WHEEL
zonar_ds_env_arg_parser-1.0.1.dist-info/top_level.txt
zonar_ds_env_arg_parser-1.0.1.dist-info/RECORD
