Metadata-Version: 2.1
Name: zonar-ds-env-arg-parser
Version: 1.0.1
Summary: An argument helper used to validate environment variables
Home-page: https://github.com/evcallia/zonar_ds_env_arg_parser.git
Author: Zonar Systems - Data Services Pod
Author-email: DSPod@zonarsystems.com
License: UNKNOWN
Keywords: zonar_ds_env_arg_parser
Platform: UNKNOWN
Classifier: Programming Language :: Python :: 3
Classifier: License :: OSI Approved :: MIT License
Classifier: Operating System :: OS Independent
